tests/__init__.py
tests/config.py
vectorio/__init__.py
vectorio/config.py
vectorio/exceptions.py
vectorio/_assets/World_UTM_Grid_HM.zip
vectorio/_assets/bkps/wkt.py.bkp
vectorio/_assets/bkps/wkt_geom_collec.py.bkp
vectorio/compress/__init__.py
vectorio/compress/icompress_engine.py
vectorio/compress/rar.py
vectorio/compress/zip_file.py
vectorio/gdal/__init__.py
vectorio/gdal/exceptions.py
vectorio/gdal/error/__init__.py
vectorio/gdal/error/custom_error.py
vectorio/gdal/error/func_decorators.py
vectorio/types/__init__.py
vectorio/vector/__init__.py
vectorio/vector/exceptions.py
vectorio/vector/_src/__init__.py
vectorio/vector/_src/gdal_aux/__init__.py
vectorio/vector/_src/gdal_aux/cloned_ds.py
vectorio/vector/_src/gdal_aux/cloned_feature.py
vectorio/vector/_src/gdal_aux/cloned_layer.py
vectorio/vector/composite/__init__.py
vectorio/vector/composite/vector_composite.py
vectorio/vector/composite/interfaces/__init__.py
vectorio/vector/composite/interfaces/ivector_composite.py
vectorio/vector/datasource/__init__.py
vectorio/vector/datasource/ds_reprojected.py
vectorio/vector/geojson/__init__.py
vectorio/vector/geojson/geojson.py
vectorio/vector/interfaces/__init__.py
vectorio/vector/interfaces/ivectorio.py
vectorio/vector/kml/__init__.py
vectorio/vector/kml/kml.py
vectorio/vector/metrics/__init__.py
vectorio/vector/metrics/vertices.py
vectorio/vector/output/__init__.py
vectorio/vector/output/geojson/__init__.py
vectorio/vector/output/geojson/feature.py
vectorio/vector/output/geojson/feature_collection.py
vectorio/vector/output/geojson/geometry.py
vectorio/vector/output/geojson/geometry_collection.py
vectorio/vector/output/wkt/__init__.py
vectorio/vector/output/wkt/geometry.py
vectorio/vector/output/wkt/geometry_collection.py
vectorio/vector/shapefile/__init__.py
vectorio/vector/shapefile/encodings.py
vectorio/vector/shapefile/file_required_by_extension.py
vectorio/vector/shapefile/shapefile.py
vectorio/vector/shapefile/decorators/__init__.py
vectorio-2.0.5.dist-info/LICENSE.txt
vectorio-2.0.5.dist-info/METADATA
vectorio-2.0.5.dist-info/WHEEL
vectorio-2.0.5.dist-info/top_level.txt
vectorio-2.0.5.dist-info/RECORD
