Metadata-Version: 2.1
Name: vectorio
Version: 2.0.5
Summary: Geoprocessing utility for working with vector data
Home-page: https://github.com/igor-rodrigues-ss/vectorio
Author: Igor Rodrigues Sousa Silva
Author-email: igor.rodrigues.ss10@gmail.com
License: UNKNOWN
Platform: UNKNOWN
Classifier: License :: OSI Approved :: MIT License
Classifier: Programming Language :: Python :: 3.6
Classifier: Programming Language :: Python :: 3.7
Classifier: Programming Language :: Python :: Implementation 
Classifier: Operating System :: OS Independent
Classifier: Development Status :: 5 - Production/Stable
Requires-Python: >=3.6
Requires-Dist: rarfile (==3.1)
Requires-Dist: typeguard (==2.9.1)
